LICENSE
MANIFEST.in
README.rst
VERSION
requirements.txt
setup.py
biotracks/__init__.py
biotracks/cmso.py
biotracks/config.py
biotracks/createdp.py
biotracks/plot.py
biotracks/pushtopandas.py
biotracks/readfile.py
biotracks/utils.py
biotracks/validation.py
biotracks.egg-info/PKG-INFO
biotracks.egg-info/SOURCES.txt
biotracks.egg-info/dependency_links.txt
biotracks.egg-info/requires.txt
biotracks.egg-info/top_level.txt
tests/__init__.py
tests/common.py
tests/test_createdp.py
tests/test_pushtopandas.py
tests/test_readfile.py
tests/test_validation.py