Metadata-Version: 1.1
Name: biotracks
Version: 0.4.1
Summary: Data package representation for cell migration tracking data
Home-page: https://github.com/CellMigStandOrg/biotracks
Author: paola masuzzo
Author-email: paola.masuzzo@ugent.be
License: BSD
Platform: UNKNOWN
Classifier: Programming Language :: Python :: 3
Classifier: License :: OSI Approved :: BSD License
Classifier: Topic :: Scientific/Engineering :: Bio-Informatics
Classifier: Intended Audience :: Science/Research
